cpp_extension.cpython-312-x86_64-linux-gnu.so
triangle/triangle.py
triangle/__init__.py
triangle_hse_opensource-1.3.dist-info/LICENSE
triangle_hse_opensource-1.3.dist-info/top_level.txt
triangle_hse_opensource-1.3.dist-info/RECORD
triangle_hse_opensource-1.3.dist-info/METADATA
triangle_hse_opensource-1.3.dist-info/WHEEL
